LICENSE
MANIFEST.in
README.rst
setup.cfg
setup.py
django_random_id_generator.egg-info/PKG-INFO
django_random_id_generator.egg-info/SOURCES.txt
django_random_id_generator.egg-info/dependency_links.txt
django_random_id_generator.egg-info/top_level.txt
generator/__init__.py
generator/settings.py
generator/urls.py
generator/wsgi.py
random_id/__init__.py
random_id/admin.py
random_id/apps.py
random_id/models.py
random_id/tests.py
random_id/utils.py
random_id/views.py
random_id/migrations/0001_initial.py
random_id/migrations/__init__.py
random_id/migrations/__pycache__/0001_initial.cpython-36.pyc
random_id/migrations/__pycache__/__init__.cpython-36.pyc